{
  "patchSchemaVersion": "1.0",
  "name": "Classic Theremin",
  "description": "A pure, sine-wave based sound reminiscent of the classic theremin, with subtle vibrato.",
  "audio": {
    "oscillatorType": "sine",
    "overtoneCount": 4,
    "attackTime": 0.04,
    "releaseTime": 0.25,
    "lfoMinFreq": 2.5,
    "lfoMaxFreqMultiplier": 2,
    "lfoMaxDepthMultiplier": 8,
    "filterCutoff": 18000,
    "filterQ": 1.0,
    "reverbMix": 0.35
  },
  "octaveOffset": 0,
  "arpeggiator": null,
  "visuals": {
    "rayDensityMultiplier": 30,
    "raySpeedMultiplier": 15,
    "rayColor": "rgba(255, 220, 100, 0.8)",
    "crosshairBaseSize": 180
  }
}